{
  "__meta": {
    "version": "0.0.1",
    "generatedAt": "2026-01-30T20:10:36.512Z",
    "targets": {
      "db0-better-sqlite3": {
        "version": "db0@0.3.4",
        "dialect": "sqlite"
      },
      "db0-libsql": {
        "version": "db0@0.3.4",
        "dialect": "sqlite"
      },
      "db0-pglite": {
        "version": "db0@0.3.4",
        "dialect": "postgresql"
      },
      "db0-sqlite3": {
        "version": "db0@0.3.4",
        "dialect": "sqlite"
      },
      "db0-node-sqlite": {
        "version": "db0@0.3.4",
        "dialect": "sqlite"
      },
      "db0-cloudflare-d1": {
        "version": "db0@0.3.4",
        "dialect": "sqlite"
      }
    }
  },
  "sql": {
    "transactions": {
      "BEGIN": {
        "description": "Explicit transaction start",
        "support": {
          "db0-better-sqlite3": {
            "supported": true
          },
          "db0-libsql": {
            "supported": true
          },
          "db0-pglite": {
            "supported": true
          },
          "db0-sqlite3": {
            "supported": true
          },
          "db0-node-sqlite": {
            "supported": true
          },
          "db0-cloudflare-d1": {
            "supported": false,
            "error": "Cannot read properties of undefined (reading 'duration')"
          }
        }
      },
      "COMMIT": {
        "description": "Commit transaction",
        "support": {
          "db0-better-sqlite3": {
            "supported": true
          },
          "db0-libsql": {
            "supported": true
          },
          "db0-pglite": {
            "supported": true
          },
          "db0-sqlite3": {
            "supported": true
          },
          "db0-node-sqlite": {
            "supported": true
          },
          "db0-cloudflare-d1": {
            "supported": false,
            "error": "Cannot read properties of undefined (reading 'duration')"
          }
        }
      },
      "ROLLBACK": {
        "description": "Rollback transaction",
        "support": {
          "db0-better-sqlite3": {
            "supported": true
          },
          "db0-libsql": {
            "supported": true
          },
          "db0-pglite": {
            "supported": true
          },
          "db0-sqlite3": {
            "supported": true
          },
          "db0-node-sqlite": {
            "supported": true
          },
          "db0-cloudflare-d1": {
            "supported": false,
            "error": "Cannot read properties of undefined (reading 'duration')"
          }
        }
      },
      "SAVEPOINT": {
        "description": "Transaction savepoints",
        "support": {
          "db0-better-sqlite3": {
            "supported": true
          },
          "db0-libsql": {
            "supported": true
          },
          "db0-pglite": {
            "supported": true
          },
          "db0-sqlite3": {
            "supported": true
          },
          "db0-node-sqlite": {
            "supported": true
          },
          "db0-cloudflare-d1": {
            "supported": false,
            "error": "Cannot read properties of undefined (reading 'duration')"
          }
        }
      },
      "batch_atomicity": {
        "description": "Atomic batch execution",
        "support": {
          "db0-better-sqlite3": {
            "supported": false,
            "notes": "Batch not atomic - partial execution"
          },
          "db0-libsql": {
            "supported": false,
            "notes": "Batch not atomic - partial execution"
          },
          "db0-pglite": {
            "supported": true
          },
          "db0-sqlite3": {
            "supported": false,
            "notes": "Batch not atomic - partial execution"
          },
          "db0-node-sqlite": {
            "supported": false,
            "notes": "Batch not atomic - partial execution"
          },
          "db0-cloudflare-d1": {
            "supported": true
          }
        }
      }
    },
    "types": {
      "type_boolean": {
        "description": "Boolean type support",
        "support": {
          "db0-better-sqlite3": {
            "supported": true
          },
          "db0-libsql": {
            "supported": true
          },
          "db0-pglite": {
            "supported": true
          },
          "db0-sqlite3": {
            "supported": true
          },
          "db0-node-sqlite": {
            "supported": true
          },
          "db0-cloudflare-d1": {
            "supported": true
          }
        }
      },
      "type_json": {
        "description": "JSON/JSONB column type",
        "support": {
          "db0-better-sqlite3": {
            "supported": true
          },
          "db0-libsql": {
            "supported": true
          },
          "db0-pglite": {
            "supported": true
          },
          "db0-sqlite3": {
            "supported": true
          },
          "db0-node-sqlite": {
            "supported": true
          },
          "db0-cloudflare-d1": {
            "supported": true
          }
        }
      },
      "type_array": {
        "description": "Array column type",
        "support": {
          "db0-better-sqlite3": {
            "supported": true
          },
          "db0-libsql": {
            "supported": true
          },
          "db0-pglite": {
            "supported": true
          },
          "db0-sqlite3": {
            "supported": true
          },
          "db0-node-sqlite": {
            "supported": true
          },
          "db0-cloudflare-d1": {
            "supported": true
          }
        }
      },
      "type_date": {
        "description": "DATE type",
        "support": {
          "db0-better-sqlite3": {
            "supported": true
          },
          "db0-libsql": {
            "supported": true
          },
          "db0-pglite": {
            "supported": true
          },
          "db0-sqlite3": {
            "supported": true
          },
          "db0-node-sqlite": {
            "supported": true
          },
          "db0-cloudflare-d1": {
            "supported": true
          }
        }
      },
      "type_timestamp": {
        "description": "TIMESTAMP type",
        "support": {
          "db0-better-sqlite3": {
            "supported": true
          },
          "db0-libsql": {
            "supported": true
          },
          "db0-pglite": {
            "supported": true
          },
          "db0-sqlite3": {
            "supported": true
          },
          "db0-node-sqlite": {
            "supported": true
          },
          "db0-cloudflare-d1": {
            "supported": true
          }
        }
      },
      "type_uuid": {
        "description": "UUID type",
        "support": {
          "db0-better-sqlite3": {
            "supported": true
          },
          "db0-libsql": {
            "supported": true
          },
          "db0-pglite": {
            "supported": true
          },
          "db0-sqlite3": {
            "supported": true
          },
          "db0-node-sqlite": {
            "supported": true
          },
          "db0-cloudflare-d1": {
            "supported": true
          }
        }
      },
      "type_bigint": {
        "description": "BIGINT type",
        "support": {
          "db0-better-sqlite3": {
            "supported": true
          },
          "db0-libsql": {
            "supported": false,
            "error": "Received integer which cannot be safely represented as a JavaScript number"
          },
          "db0-pglite": {
            "supported": true
          },
          "db0-sqlite3": {
            "supported": true
          },
          "db0-node-sqlite": {
            "supported": false,
            "error": "Value is too large to be represented as a JavaScript number: 9223372036854775807"
          },
          "db0-cloudflare-d1": {
            "supported": true
          }
        }
      },
      "type_decimal": {
        "description": "DECIMAL/NUMERIC type",
        "support": {
          "db0-better-sqlite3": {
            "supported": true
          },
          "db0-libsql": {
            "supported": true
          },
          "db0-pglite": {
            "supported": true
          },
          "db0-sqlite3": {
            "supported": true
          },
          "db0-node-sqlite": {
            "supported": true
          },
          "db0-cloudflare-d1": {
            "supported": true
          }
        }
      }
    },
    "json": {
      "JSON_EXTRACT": {
        "description": "Extract JSON values",
        "support": {
          "db0-better-sqlite3": {
            "supported": true,
            "notes": "json_extract function"
          },
          "db0-libsql": {
            "supported": true,
            "notes": "json_extract function"
          },
          "db0-pglite": {
            "supported": true,
            "notes": "PostgreSQL JSONB syntax"
          },
          "db0-sqlite3": {
            "supported": true,
            "notes": "json_extract function"
          },
          "db0-node-sqlite": {
            "supported": true,
            "notes": "json_extract function"
          },
          "db0-cloudflare-d1": {
            "supported": true,
            "notes": "json_extract function"
          }
        }
      },
      "JSON_SET": {
        "description": "Modify JSON values",
        "support": {
          "db0-better-sqlite3": {
            "supported": true,
            "notes": "json_set function"
          },
          "db0-libsql": {
            "supported": true,
            "notes": "json_set function"
          },
          "db0-pglite": {
            "supported": true,
            "notes": "PostgreSQL jsonb_set"
          },
          "db0-sqlite3": {
            "supported": true,
            "notes": "json_set function"
          },
          "db0-node-sqlite": {
            "supported": true,
            "notes": "json_set function"
          },
          "db0-cloudflare-d1": {
            "supported": true,
            "notes": "json_set function"
          }
        }
      },
      "JSON_ARRAY": {
        "description": "Create JSON arrays",
        "support": {
          "db0-better-sqlite3": {
            "supported": true,
            "notes": "json_array function"
          },
          "db0-libsql": {
            "supported": true,
            "notes": "json_array function"
          },
          "db0-pglite": {
            "supported": true,
            "notes": "PostgreSQL jsonb_build_array"
          },
          "db0-sqlite3": {
            "supported": true,
            "notes": "json_array function"
          },
          "db0-node-sqlite": {
            "supported": true,
            "notes": "json_array function"
          },
          "db0-cloudflare-d1": {
            "supported": true,
            "notes": "json_array function"
          }
        }
      },
      "jsonb_operators": {
        "description": "PostgreSQL JSONB operators (@>, ->, etc.)",
        "support": {
          "db0-better-sqlite3": {
            "supported": false,
            "notes": "PostgreSQL-specific feature",
            "error": "unrecognized token: \":\""
          },
          "db0-libsql": {
            "supported": false,
            "notes": "PostgreSQL-specific feature",
            "error": "SQLITE_ERROR: unrecognized token: \":\""
          },
          "db0-pglite": {
            "supported": true
          },
          "db0-sqlite3": {
            "supported": false,
            "notes": "PostgreSQL-specific feature",
            "error": "SQLITE_ERROR: unrecognized token: \":\""
          },
          "db0-node-sqlite": {
            "supported": false,
            "notes": "PostgreSQL-specific feature",
            "error": "unrecognized token: \":\""
          },
          "db0-cloudflare-d1": {
            "supported": false,
            "notes": "PostgreSQL-specific feature",
            "error": "D1_ERROR: unrecognized token: \":\" at offset 25: SQLITE_ERROR"
          }
        }
      }
    },
    "queries": {
      "RETURNING": {
        "description": "RETURNING clause",
        "support": {
          "db0-better-sqlite3": {
            "supported": true
          },
          "db0-libsql": {
            "supported": true
          },
          "db0-pglite": {
            "supported": true
          },
          "db0-sqlite3": {
            "supported": true
          },
          "db0-node-sqlite": {
            "supported": true
          },
          "db0-cloudflare-d1": {
            "supported": true
          }
        }
      },
      "UPSERT_on_conflict": {
        "description": "ON CONFLICT clause (PostgreSQL/SQLite)",
        "support": {
          "db0-better-sqlite3": {
            "supported": true
          },
          "db0-libsql": {
            "supported": true
          },
          "db0-pglite": {
            "supported": true
          },
          "db0-sqlite3": {
            "supported": true
          },
          "db0-node-sqlite": {
            "supported": true
          },
          "db0-cloudflare-d1": {
            "supported": true
          }
        }
      },
      "UPSERT_on_duplicate": {
        "description": "ON DUPLICATE KEY (MySQL)",
        "support": {
          "db0-better-sqlite3": {
            "supported": false,
            "notes": "MySQL-specific syntax",
            "error": "near \"DUPLICATE\": syntax error"
          },
          "db0-libsql": {
            "supported": false,
            "notes": "MySQL-specific syntax",
            "error": "SQLITE_ERROR: near \"DUPLICATE\": syntax error"
          },
          "db0-pglite": {
            "supported": false,
            "notes": "MySQL-specific syntax",
            "error": "syntax error at or near \"DUPLICATE\""
          },
          "db0-sqlite3": {
            "supported": false,
            "notes": "MySQL-specific syntax",
            "error": "SQLITE_ERROR: near \"DUPLICATE\": syntax error"
          },
          "db0-node-sqlite": {
            "supported": false,
            "notes": "MySQL-specific syntax",
            "error": "near \"DUPLICATE\": syntax error"
          },
          "db0-cloudflare-d1": {
            "supported": false,
            "notes": "MySQL-specific syntax",
            "error": "Cannot read properties of undefined (reading 'duration')"
          }
        }
      },
      "UPSERT_replace": {
        "description": "REPLACE INTO (SQLite)",
        "support": {
          "db0-better-sqlite3": {
            "supported": true
          },
          "db0-libsql": {
            "supported": true
          },
          "db0-pglite": {
            "supported": false,
            "notes": "SQLite/MySQL syntax",
            "error": "syntax error at or near \"REPLACE\""
          },
          "db0-sqlite3": {
            "supported": true
          },
          "db0-node-sqlite": {
            "supported": true
          },
          "db0-cloudflare-d1": {
            "supported": true
          }
        }
      },
      "CTE": {
        "description": "Common Table Expressions (WITH)",
        "support": {
          "db0-better-sqlite3": {
            "supported": false
          },
          "db0-libsql": {
            "supported": true
          },
          "db0-pglite": {
            "supported": true
          },
          "db0-sqlite3": {
            "supported": false
          },
          "db0-node-sqlite": {
            "supported": false
          },
          "db0-cloudflare-d1": {
            "supported": false
          }
        }
      },
      "CTE_recursive": {
        "description": "Recursive CTEs (WITH RECURSIVE)",
        "support": {
          "db0-better-sqlite3": {
            "supported": false
          },
          "db0-libsql": {
            "supported": true
          },
          "db0-pglite": {
            "supported": true
          },
          "db0-sqlite3": {
            "supported": false
          },
          "db0-node-sqlite": {
            "supported": false
          },
          "db0-cloudflare-d1": {
            "supported": false
          }
        }
      },
      "window_functions": {
        "description": "Window functions (ROW_NUMBER, etc.)",
        "support": {
          "db0-better-sqlite3": {
            "supported": true
          },
          "db0-libsql": {
            "supported": true
          },
          "db0-pglite": {
            "supported": true
          },
          "db0-sqlite3": {
            "supported": true
          },
          "db0-node-sqlite": {
            "supported": true
          },
          "db0-cloudflare-d1": {
            "supported": true
          }
        }
      },
      "LIMIT_OFFSET": {
        "description": "LIMIT and OFFSET",
        "support": {
          "db0-better-sqlite3": {
            "supported": true
          },
          "db0-libsql": {
            "supported": true
          },
          "db0-pglite": {
            "supported": true
          },
          "db0-sqlite3": {
            "supported": true
          },
          "db0-node-sqlite": {
            "supported": true
          },
          "db0-cloudflare-d1": {
            "supported": true
          }
        }
      },
      "subqueries": {
        "description": "Subqueries",
        "support": {
          "db0-better-sqlite3": {
            "supported": true
          },
          "db0-libsql": {
            "supported": true
          },
          "db0-pglite": {
            "supported": true
          },
          "db0-sqlite3": {
            "supported": true
          },
          "db0-node-sqlite": {
            "supported": true
          },
          "db0-cloudflare-d1": {
            "supported": true
          }
        }
      }
    },
    "fts": {
      "FTS_basic": {
        "description": "Full-text search",
        "support": {
          "db0-better-sqlite3": {
            "supported": true,
            "notes": "SQLite FTS5"
          },
          "db0-libsql": {
            "supported": true,
            "notes": "SQLite FTS5"
          },
          "db0-pglite": {
            "supported": true,
            "notes": "PostgreSQL tsvector"
          },
          "db0-sqlite3": {
            "supported": true,
            "notes": "SQLite FTS5"
          },
          "db0-node-sqlite": {
            "supported": true,
            "notes": "SQLite FTS5"
          },
          "db0-cloudflare-d1": {
            "supported": true,
            "notes": "SQLite FTS5"
          }
        }
      },
      "FTS_ranking": {
        "description": "FTS ranking/scoring",
        "support": {
          "db0-better-sqlite3": {
            "supported": true,
            "notes": "SQLite FTS5 bm25"
          },
          "db0-libsql": {
            "supported": true,
            "notes": "SQLite FTS5 bm25"
          },
          "db0-pglite": {
            "supported": true,
            "notes": "PostgreSQL ts_rank"
          },
          "db0-sqlite3": {
            "supported": true,
            "notes": "SQLite FTS5 bm25"
          },
          "db0-node-sqlite": {
            "supported": true,
            "notes": "SQLite FTS5 bm25"
          },
          "db0-cloudflare-d1": {
            "supported": true,
            "notes": "SQLite FTS5 bm25"
          }
        }
      }
    },
    "constraints": {
      "foreign_keys": {
        "description": "Foreign key constraints",
        "support": {
          "db0-better-sqlite3": {
            "supported": true
          },
          "db0-libsql": {
            "supported": true
          },
          "db0-pglite": {
            "supported": true
          },
          "db0-sqlite3": {
            "supported": true
          },
          "db0-node-sqlite": {
            "supported": true
          },
          "db0-cloudflare-d1": {
            "supported": true
          }
        }
      },
      "CHECK_constraint": {
        "description": "CHECK constraints",
        "support": {
          "db0-better-sqlite3": {
            "supported": true
          },
          "db0-libsql": {
            "supported": true
          },
          "db0-pglite": {
            "supported": true
          },
          "db0-sqlite3": {
            "supported": true
          },
          "db0-node-sqlite": {
            "supported": true
          },
          "db0-cloudflare-d1": {
            "supported": true
          }
        }
      },
      "UNIQUE_constraint": {
        "description": "UNIQUE constraints",
        "support": {
          "db0-better-sqlite3": {
            "supported": true
          },
          "db0-libsql": {
            "supported": true
          },
          "db0-pglite": {
            "supported": true
          },
          "db0-sqlite3": {
            "supported": true
          },
          "db0-node-sqlite": {
            "supported": true
          },
          "db0-cloudflare-d1": {
            "supported": true
          }
        }
      }
    },
    "other": {
      "prepared_statements": {
        "description": "Prepared statements",
        "support": {
          "db0-better-sqlite3": {
            "supported": true
          },
          "db0-libsql": {
            "supported": true
          },
          "db0-pglite": {
            "supported": true
          },
          "db0-sqlite3": {
            "supported": true
          },
          "db0-node-sqlite": {
            "supported": true
          },
          "db0-cloudflare-d1": {
            "supported": true
          }
        }
      },
      "EXPLAIN": {
        "description": "Query explain/analysis",
        "support": {
          "db0-better-sqlite3": {
            "supported": false
          },
          "db0-libsql": {
            "supported": true
          },
          "db0-pglite": {
            "supported": true
          },
          "db0-sqlite3": {
            "supported": false
          },
          "db0-node-sqlite": {
            "supported": false
          },
          "db0-cloudflare-d1": {
            "supported": false
          }
        }
      }
    }
  },
  "db0": {
    "api": {
      "db0_sql_template": {
        "description": "sql tagged template for params",
        "support": {
          "db0-better-sqlite3": {
            "supported": true
          },
          "db0-libsql": {
            "supported": true
          },
          "db0-pglite": {
            "supported": true
          },
          "db0-sqlite3": {
            "supported": true
          },
          "db0-node-sqlite": {
            "supported": true
          },
          "db0-cloudflare-d1": {
            "supported": true
          }
        }
      },
      "db0_exec": {
        "description": "Raw SQL execution via exec()",
        "support": {
          "db0-better-sqlite3": {
            "supported": true
          },
          "db0-libsql": {
            "supported": true
          },
          "db0-pglite": {
            "supported": true
          },
          "db0-sqlite3": {
            "supported": true
          },
          "db0-node-sqlite": {
            "supported": true
          },
          "db0-cloudflare-d1": {
            "supported": true
          }
        }
      },
      "db0_batch": {
        "description": "Multi-statement batch execution",
        "support": {
          "db0-better-sqlite3": {
            "supported": true
          },
          "db0-libsql": {
            "supported": false
          },
          "db0-pglite": {
            "supported": false,
            "error": "cannot insert multiple commands into a prepared statement"
          },
          "db0-sqlite3": {
            "supported": true
          },
          "db0-node-sqlite": {
            "supported": true
          },
          "db0-cloudflare-d1": {
            "supported": true
          }
        }
      },
      "db0_prepare": {
        "description": "Prepared statement API",
        "support": {
          "db0-better-sqlite3": {
            "supported": true
          },
          "db0-libsql": {
            "supported": true
          },
          "db0-pglite": {
            "supported": true
          },
          "db0-sqlite3": {
            "supported": true
          },
          "db0-node-sqlite": {
            "supported": true
          },
          "db0-cloudflare-d1": {
            "supported": true
          }
        }
      },
      "db0_first": {
        "description": "First row helper",
        "support": {
          "db0-better-sqlite3": {
            "supported": true
          },
          "db0-libsql": {
            "supported": true
          },
          "db0-pglite": {
            "supported": true
          },
          "db0-sqlite3": {
            "supported": true
          },
          "db0-node-sqlite": {
            "supported": true
          },
          "db0-cloudflare-d1": {
            "supported": true
          }
        }
      },
      "db0_rows": {
        "description": "Rows array access",
        "support": {
          "db0-better-sqlite3": {
            "supported": true
          },
          "db0-libsql": {
            "supported": true
          },
          "db0-pglite": {
            "supported": true
          },
          "db0-sqlite3": {
            "supported": true
          },
          "db0-node-sqlite": {
            "supported": true
          },
          "db0-cloudflare-d1": {
            "supported": true
          }
        }
      }
    },
    "connection": {
      "db0_close": {
        "description": "Connection cleanup",
        "support": {
          "db0-better-sqlite3": {
            "supported": false,
            "notes": "close() method not available"
          },
          "db0-libsql": {
            "supported": false,
            "notes": "close() method not available"
          },
          "db0-pglite": {
            "supported": false,
            "notes": "close() method not available"
          },
          "db0-sqlite3": {
            "supported": false,
            "notes": "close() method not available"
          },
          "db0-node-sqlite": {
            "supported": false,
            "notes": "close() method not available"
          },
          "db0-cloudflare-d1": {
            "supported": false,
            "notes": "close() method not available"
          }
        }
      },
      "db0_transaction": {
        "description": "Transaction helper API",
        "support": {
          "db0-better-sqlite3": {
            "supported": true
          },
          "db0-libsql": {
            "supported": true
          },
          "db0-pglite": {
            "supported": true
          },
          "db0-sqlite3": {
            "supported": true
          },
          "db0-node-sqlite": {
            "supported": true
          },
          "db0-cloudflare-d1": {
            "supported": false,
            "error": "Cannot read properties of undefined (reading 'duration')"
          }
        }
      }
    }
  }
}